{
    "asset": {
        "id": "0d61df7ad3cff1910c11da73f9491b4c",
        "format": "JPG",
        "state": 2,
        "type": 1,
        "name": "IMG_4301.JPG",
        "path": "https://surftestvott.blob.core.windows.net/input/IMG_4301.JPG?sv=2018-03-28&ss=b&srt=sco&sp=rwdlac&se=2019-09-13T23:25:10Z&st=2019-06-13T15:25:10Z&spr=https&sig=ZyIJgyVpKoohY6jGZX4Ovcj626VrPw7Cwu6uk0C0qHk%3D",
        "size": {
            "width": 6000,
            "height": 4000
        }
    },
    "regions": [
        {
            "id": "UlU1uChos",
            "type": "POLYGON",
            "tags": [
                "drinking_bottle"
            ],
            "boundingBox": {
                "height": 540.272614622057,
                "width": 242.77456647398844,
                "left": 2838.976052848885,
                "top": 1738.1505576208178
            },
            "points": [
                {
                    "x": 2908.3402146985964,
                    "y": 1757.9770755885997
                },
                {
                    "x": 2883.5672997522706,
                    "y": 1966.1555142503096
                },
                {
                    "x": 2838.976052848885,
                    "y": 2104.941140024783
                },
                {
                    "x": 2858.7943848059454,
                    "y": 2223.9002478314746
                },
                {
                    "x": 2843.9306358381505,
                    "y": 2278.423172242875
                },
                {
                    "x": 2913.2947976878613,
                    "y": 2268.509913258984
                },
                {
                    "x": 2928.1585466556567,
                    "y": 2199.1171003717473
                },
                {
                    "x": 3012.3864574731624,
                    "y": 2020.6784386617098
                },
                {
                    "x": 3081.7506193228737,
                    "y": 1738.1505576208178
                }
            ]
        },
        {
            "id": "XG31rczFw",
            "type": "POLYGON",
            "tags": [
                "fragment"
            ],
            "boundingBox": {
                "height": 1407.6827757125154,
                "width": 465.7308009909166,
                "left": 1312.9644921552435,
                "top": 702.2149938042131
            },
            "points": [
                {
                    "x": 1674.6490503715936,
                    "y": 702.2149938042131
                },
                {
                    "x": 1610.2394715111477,
                    "y": 756.7379182156134
                },
                {
                    "x": 1555.739058629232,
                    "y": 875.6970260223047
                },
                {
                    "x": 1412.056151940545,
                    "y": 1064.0489467162329
                },
                {
                    "x": 1387.2832369942196,
                    "y": 1217.7044609665427
                },
                {
                    "x": 1372.4194880264245,
                    "y": 1386.229863692689
                },
                {
                    "x": 1352.6011560693642,
                    "y": 1569.6251548946716
                },
                {
                    "x": 1312.9644921552435,
                    "y": 1802.5867410161088
                },
                {
                    "x": 1327.8282411230389,
                    "y": 2055.3748451053284
                },
                {
                    "x": 1466.5565648224608,
                    "y": 2109.8977695167287
                },
                {
                    "x": 1615.194054500413,
                    "y": 1971.112143742255
                },
                {
                    "x": 1575.5573905862923,
                    "y": 1673.7143742255266
                },
                {
                    "x": 1654.8307184145335,
                    "y": 1807.5433705080543
                },
                {
                    "x": 1699.421965317919,
                    "y": 1673.7143742255266
                },
                {
                    "x": 1778.69529314616,
                    "y": 1604.32156133829
                },
                {
                    "x": 1704.376548307184,
                    "y": 1187.9646840148698
                }
            ]
        }
    ],
    "version": "2.1.0"
}