{
    "asset": {
        "id": "1aab1264f24c20fb0f2a5b1e5edbfb1c",
        "format": "JPG",
        "state": 2,
        "type": 1,
        "name": "IMG_4053.JPG",
        "path": "https://surftestvott.blob.core.windows.net/input/IMG_4053.JPG?sv=2018-03-28&ss=b&srt=sco&sp=rwdlac&se=2019-09-13T23:25:10Z&st=2019-06-13T15:25:10Z&spr=https&sig=ZyIJgyVpKoohY6jGZX4Ovcj626VrPw7Cwu6uk0C0qHk%3D",
        "size": {
            "width": 6000,
            "height": 4000
        }
    },
    "regions": [
        {
            "id": "8GLwTaB6c",
            "type": "POLYGON",
            "tags": [
                "other"
            ],
            "boundingBox": {
                "height": 525.4027261462205,
                "width": 312.1387283236994,
                "left": 4815.854665565648,
                "top": 1212.7478314745972
            },
            "points": [
                {
                    "x": 4865.400495458299,
                    "y": 1212.7478314745972
                },
                {
                    "x": 4815.854665565648,
                    "y": 1267.2707558859975
                },
                {
                    "x": 4974.401321222131,
                    "y": 1401.0997521685254
                },
                {
                    "x": 4954.58298926507,
                    "y": 1634.0613382899628
                },
                {
                    "x": 5088.356729975227,
                    "y": 1738.1505576208178
                },
                {
                    "x": 5123.038810900082,
                    "y": 1634.0613382899628
                },
                {
                    "x": 5127.993393889347,
                    "y": 1564.6685254027261
                }
            ]
        }
    ],
    "version": "2.1.0"
}